nesiac/__main__.py
nesiac/args.py
nesiac/cli.py
nesiac/ingest.py
nesiac/parsing/__init__.py
nesiac/parsing/map_regions.py
nesiac/parsing/objects.py
nesiac/parsing/program_headers.py
nesiac/parsing/section_headers.py
nesiac-0.4.4.dist-info/entry_points.txt
nesiac-0.4.4.dist-info/LICENSE
nesiac-0.4.4.dist-info/METADATA
nesiac-0.4.4.dist-info/WHEEL
nesiac-0.4.4.dist-info/RECORD
