Metadata-Version: 2.3
Name: nesiac
Version: 0.4.4
Summary: Memory usage visualiser for embedded applications
Home-page: https://github.com/Eekle/Nesiac/
License: MIT
Keywords: embedded,elf,binary,memory
Author: Eekle
Requires-Python: >=3.9,<4.0
Classifier: License :: OSI Approved :: MIT License
Classifier: Programming Language :: Python :: 3
Classifier: Programming Language :: Python :: 3.9
Classifier: Programming Language :: Python :: 3.10
Classifier: Programming Language :: Python :: 3.11
Classifier: Programming Language :: Python :: 3.12
Classifier: Programming Language :: Python :: 3.13
Classifier: Topic :: Software Development :: Embedded Systems
Requires-Dist: cxxfilt (>=0.3.0,<0.4.0)
Requires-Dist: getchlib (>=1.0.12,<2.0.0)
Requires-Dist: pyelftools (>=0.30,<0.31)
Requires-Dist: rich (>=13.6.0,<14.0.0)
Requires-Dist: rust-demangler (>=1.0,<2.0)
Project-URL: Repository, https://github.com/Eekle/Nesiac/
